pymetastore-0.4.2.dist-info/METADATA
pymetastore-0.4.2.dist-info/WHEEL
pymetastore-0.4.2.dist-info/entry_points.txt
pymetastore-0.4.2.dist-info/licenses/LICENSE
pymetastore/__init__.py
pymetastore/hive_metastore/ThriftHiveMetastore-remote
pymetastore/hive_metastore/ThriftHiveMetastore.py
pymetastore/hive_metastore/__init__.py
pymetastore/hive_metastore/constants.py
pymetastore/hive_metastore/ttypes.py
pymetastore/htypes.py
pymetastore/metastore.py
pymetastore/stats.py
pymetastore-0.4.2.dist-info/RECORD
