Metadata-Version: 2.1
Name: pymetastore
Version: 0.4.2
Summary: A Python client for the Thrift interface to Hive Metastore
Keywords: data,data catalog,data discovery,data engineering,data governance,data infrastructure,data integration,data pipelines,hcatalog,hive,hive metastore,metadata,metastore,thrift,python,recap
Author: Kostas Pardalis
Author-Email: Chris Riccomini <criccomini@apache.org>
License: MIT
Project-URL: repository, https://github.com/recap-build/pymetastore
Requires-Python: >=3.8
Requires-Dist: thrift>=0.16.0
